adder.v

// half_adder module: This module computes the sum and carry-out of two single-bit inputs.

module half(
    input a,b,
    output sum, carry
);

    assign sum = a^b;
    assign carry = a&b;

endmodule

// full_adder module: This module computes the sum and carry-out of three single-bit inputs (a, b, and cin) by using two half-adder modules and an OR gate.

module fulladd(
    input a,b, cin,
    output sum, cout
);

    // Wires to connect the outputs of the first half-adder to the inputs of the second half-adder and the final OR gate.

    wire sum1, c2, c1;

    half ha1(.a(a), .b(b), .sum(sum1), .carry(c1));

    half ha2(.a(sum1), .b(cin), .sum(sum), .carry(c2));

    or(cout,c1,c2);

endmodule

adder_tb.v
module full_adder_tb;

    // Declare testbench signals for the DUT's inputs and outputs
    reg a, b, cin;       // Inputs are declared as 'reg'
    wire sum, cout;      // Outputs are declared as 'wire'

    // Instantiate the DUT (Design Under Test)

    fulladd DUT (
        .a(a),
        .b(b),
        .cin(cin),
        .sum(sum),
        .cout(cout)
    );

    // Initial block to apply stimulus and run the simulation
    initial begin
        // Open the waveform dump file for GTKWave
        $dumpfile("full_adder.vcd");
        // Dump all signals in the DUT for viewing
        $dumpvars(0, DUT);

        // Apply all 8 possible input combinations (2^3 = 8)

        a = 0; b = 0; cin = 0;
        #10;
        a = 0; b = 0; cin = 1;
        #10;
       a = 0; b = 1; cin = 0;
        #10;
        a = 0; b = 1; cin = 1;
        #10;
        a = 1; b = 0; cin = 0;
        #10;
        a = 1; b = 0; cin = 1;
        #10;
        a = 1; b = 1; cin = 0;
        #10;
       a = 1; b = 1; cin = 1;
        #10;
    
        $monitor("Time = %0t, a = %b, b = %b, sum = %b, carry = %b", $time, a, b, sum, cout);

        $finish;

    end
endmodule

full_adder.vcd
$date
	Thu Aug 28 16:38:18 2025
$end
$version
	Icarus Verilog
$end
$timescale
	1s
$end
$scope module full_adder_tb $end
$scope module DUT $end
$var wire 1 ! a $end
$var wire 1 " b $end
$var wire 1 # c1 $end
$var wire 1 $ c2 $end
$var wire 1 % cin $end
$var wire 1 & cout $end
$var wire 1 ' sum $end
$var wire 1 ( sum1 $end
$scope module ha1 $end
$var wire 1 ! a $end
$var wire 1 " b $end
$var wire 1 # carry $end
$var wire 1 ( sum $end
$upscope $end
$scope module ha2 $end
$var wire 1 ( a $end
$var wire 1 % b $end
$var wire 1 $ carry $end
$var wire 1 ' sum $end
$upscope $end
$upscope $end
$upscope $end
$enddefinitions $end
#0
$dumpvars
0(
0'
0&
0%
0$
0#
0"
0!
$end
#10
1'
1%
#20
1(
0%
1"
#30
1&
0'
1$
1%
#40
0&
1'
0$
0%
0"
1!
#50
1&
0'
1$
1%
#60
0$
0(
1#
0%
1"
#70
1'
1%
